pyloid_watcher/__init__.py
pyloid_watcher/cli.py
pyloid_watcher/watcher.py
pyloid_watcher-0.1.8.dist-info/METADATA
pyloid_watcher-0.1.8.dist-info/WHEEL
pyloid_watcher-0.1.8.dist-info/entry_points.txt
pyloid_watcher-0.1.8.dist-info/RECORD
