Metadata-Version: 2.4
Name: pyloid-watcher
Version: 0.1.8
Summary: Cross-platform Pyloid backend file watcher with auto-restart
Requires-Python: >=3.9
Requires-Dist: watchdog>=6.0.0
